[
  {
    "id": "mon_cat_mutant_prism",
    "type": "MONSTER",
    "name": { "str": "iridescent cat" },
    "description": "As it moves, this cat's colors shift unnaturally in the light.  You can't make out the breed, but its fur pattern seems to change with every step.",
    "volume": "4000 ml",
    "weight": "4 kg",
    "//": "Higher dodge due to the constantly changing fur pattern",
    "dodge": 9,
    "hp": 6,
    "harvest": "mammal_tiny",
    "melee_damage": [ { "damage_type": "cut", "amount": 1 } ],
    "special_attacks": [ { "id": "scratch", "attack_upper": false, "cooldown": 10 } ],
    "flags": [
      "SEES",
      "HEARS",
      "GOODHEARING",
      "SMELLS",
      "ANIMAL",
      "CANPLAY",
      "PATH_AVOID_DANGER_1",
      "WARM",
      "HIT_AND_RUN",
      "CORNERED_FIGHTER",
      "NO_BREED"
    ],
    "upgrades": { "age_grow": 120, "into": "mon_cat" },
    "//": "Kittens do not have their full fur yet and are really sensitive to cold temperature",
    "armor": { "cold": 0 }
  },
  {
    "id": "mon_cat_liquid",
    "type": "MONSTER",
    "name": { "str": "liquid cat" },
    "description": "It is universally known that cats are liquid, but this cat's body is actually quivering while it walks around.  It also enjoys resting while twisting its body in ways that would break a normal cat's bones.",
    "default_faction": "cat",
    "bodytype": "dog",
    "categories": [ "WILDLIFE" ],
    "species": [ "MAMMAL" ],
    "hp": 12,
    "speed": 150,
    "material": [ "flesh" ],
    "symbol": "c",
    "color": "light_gray",
    "aggression": -99,
    "morale": 2,
    "melee_skill": 6,
    "melee_dice": 1,
    "melee_dice_sides": 2,
    "melee_damage": [ { "damage_type": "cut", "amount": 2 } ],
    "dodge": 8,
    "//": "Their fur keeps them warm",
    "vision_night": 20,
    "special_attacks": [
      { "id": "scratch", "attack_upper": false, "cooldown": 10 },
      { "type": "bite", "cooldown": 15, "infection_chance": 50 }
    ],
    "fear_triggers": [ "SOUND", "PLAYER_CLOSE", "FRIEND_ATTACKED" ],
    "placate_triggers": [ "PLAYER_WEAK" ],
    "dissect": "dissect_feline_sample_single",
    "families": [ "prof_intro_biology" ],
    "reproduction": { "baby_monster": "mon_cat_kitten", "baby_count": 4, "baby_timer": 60 },
    "petfood": {
      "food": [ "CATFOOD" ],
      "feed": "The %s seems to like you!  Or maybe it just tolerates your presence better.  It's hard to tell with felines.",
      "pet": "The %s softly purrs as you pet it.  It demands more."
    },
    "volume": "5000 ml",
    "weight": "5 kg",
    "phase": "LIQUID",
    "harvest": "exempt",
    "death_function": { "corpse_type": "NO_CORPSE", "message": "The %s's body splashes one last time." }
  },
  {
    "id": "mon_cat_void",
    "type": "MONSTER",
    "name": { "str": "void cat" },
    "description": "Seeing how unnaturally dark this black cat's fur is, you are certain this is no ordinary cat.  Its fur seems to absorb light from the surroundings.",
    "volume": "4000 ml",
    "weight": "4 kg",
    "regenerates_in_dark": true,
    "default_faction": "cat",
    "bodytype": "dog",
    "categories": [ "WILDLIFE" ],
    "species": [ "MAMMAL" ],
    "hp": 12,
    "speed": 150,
    "material": [ "flesh" ],
    "symbol": "c",
    "aggression": -99,
    "morale": 2,
    "melee_skill": 6,
    "melee_dice": 1,
    "melee_dice_sides": 2,
    "melee_damage": [ { "damage_type": "cut", "amount": 2 } ],
    "dodge": 8,
    "//": "Their fur keeps them warm",
    "special_attacks": [
      { "id": "scratch", "attack_upper": false, "cooldown": 10 },
      { "type": "bite", "cooldown": 15, "infection_chance": 50 }
    ],
    "fear_triggers": [ "SOUND", "PLAYER_CLOSE", "FRIEND_ATTACKED" ],
    "placate_triggers": [ "PLAYER_WEAK" ],
    "harvest": "cat_small_with_skull",
    "dissect": "dissect_feline_sample_single",
    "families": [ "prof_intro_biology" ],
    "reproduction": { "baby_monster": "mon_cat_kitten", "baby_count": 4, "baby_timer": 60 },
    "petfood": {
      "food": [ "CATFOOD" ],
      "feed": "The %s seems to like you!  Or maybe it just tolerates your presence better.  It's hard to tell with felines.",
      "pet": "The %s softly purrs as you pet it.  It demands more."
    }
  },
  {
    "id": "mon_dog_incorporeal",
    "type": "MONSTER",
    "name": { "str": "translucent dog" },
    "description": "This dog doesn't cast a shadow, and if you squint hard enough you can see right through it.  Its condition doesn't appear to do any harm to it, though it seems to cause trouble when it tries to groom itself.",
    "volume": "30000 ml",
    "weight": "30 kg",
    "color": "white",
    "vision_night": 4,
    "default_faction": "dog",
    "bodytype": "dog",
    "categories": [ "WILDLIFE" ],
    "species": [ "MAMMAL" ],
    "harvest": "dog_with_skull_fur",
    "dissect": "dissect_lupine_sample_single",
    "hp": 30,
    "speed": 150,
    "material": [ "flesh" ],
    "symbol": "d",
    "aggression": -10,
    "morale": 15,
    "aggro_character": false,
    "melee_skill": 6,
    "melee_dice": 2,
    "melee_dice_sides": 3,
    "melee_damage": [ { "damage_type": "cut", "amount": 3 } ],
    "dodge": 3,
    "zombify_into": "mon_zombie_dog",
    "death_drops": "mon_dog_death_drops",
    "families": [ "prof_intro_biology" ],
    "path_settings": { "max_dist": 10 },
    "reproduction": { "baby_monster": "mon_dog_pup", "baby_count": 4, "baby_timer": 270 },
    "//": "1-4 puppies & 270 days per-litter for size small canines",
    "baby_flags": [ "SPRING", "SUMMER", "AUTUMN", "WINTER" ],
    "biosignature": { "biosig_item": "feces_dog", "biosig_timer": 6 },
    "anger_triggers": [ "HURT", "FRIEND_ATTACKED", "FRIEND_DIED" ],
    "special_attacks": [ [ "EAT_FOOD", 100 ], [ "PARROT_AT_DANGER", 0 ] ],
    "petfood": {
      "food": [ "DOGFOOD" ],
      "feed": "The %s seems to like you!  It lets you pat its head and seems friendly.",
      "pet": "The %s happily wags its tail while you pat its head."
    },
    "flags": [
      "ANIMAL",
      "DOGFOOD",
      "CANPLAY",
      "CAN_BE_CULLED",
      "GROUP_MORALE",
      "HEARS",
      "PET_MOUNTABLE",
      "HIT_AND_RUN",
      "KEENNOSE",
      "PATH_AVOID_DANGER_1",
      "SEES",
      "SMELLS",
      "SWARMS",
      "WARM",
      "CORNERED_FIGHTER"
    ]
  },
  {
    "id": "mon_dog_telekenetic",
    "type": "MONSTER",
    "name": { "str": "triclopean dog" },
    "description": "A rather average looking dog until you notice the third eye, right on its forehead, covered by a thick eyelid.  Whenever its open, small particles of dust from the ground rise and swirl around it.",
    "default_faction": "dog",
    "bodytype": "dog",
    "categories": [ "WILDLIFE" ],
    "species": [ "MAMMAL" ],
    "volume": "25000 ml",
    "weight": "25 kg",
    "harvest": "dog_triclopean_with_skull",
    "dissect": "dissect_lupine_sample_single",
    "hp": 30,
    "speed": 150,
    "material": [ "flesh" ],
    "symbol": "d",
    "color": "light_gray",
    "aggression": -10,
    "morale": 15,
    "aggro_character": false,
    "melee_skill": 6,
    "melee_dice": 2,
    "melee_dice_sides": 3,
    "melee_damage": [ { "damage_type": "cut", "amount": 3 } ],
    "dodge": 3,
    "vision_night": 5,
    "zombify_into": "mon_zombie_dog",
    "death_drops": "mon_dog_death_drops",
    "families": [ "prof_intro_biology" ],
    "path_settings": { "max_dist": 10 },
    "reproduction": { "baby_monster": "mon_dog_pup", "baby_count": 4, "baby_timer": 270 },
    "//": "1-4 puppies & 270 days per-litter for size small canines",
    "baby_flags": [ "SPRING", "SUMMER", "AUTUMN", "WINTER" ],
    "biosignature": { "biosig_item": "feces_dog", "biosig_timer": 6 },
    "anger_triggers": [ "HURT", "FRIEND_ATTACKED", "FRIEND_DIED" ],
    "special_attacks": [ [ "EAT_FOOD", 100 ], [ "PARROT_AT_DANGER", 0 ] ],
    "petfood": {
      "food": [ "DOGFOOD" ],
      "feed": "The %s seems to like you!  It lets you pat its head and seems friendly.",
      "pet": "The %s happily wags its tail while you pat its head."
    },
    "flags": [
      "ANIMAL",
      "DOGFOOD",
      "CANPLAY",
      "CAN_BE_CULLED",
      "GROUP_MORALE",
      "HEARS",
      "PET_MOUNTABLE",
      "HIT_AND_RUN",
      "KEENNOSE",
      "PATH_AVOID_DANGER_1",
      "SEES",
      "SMELLS",
      "SWARMS",
      "WARM",
      "CORNERED_FIGHTER"
    ]
  },
  {
    "id": "mon_dog_antimemetic",
    "type": "MONSTER",
    "name": { "str": "unknowable dog" },
    "description": "You are completely unable to recall anything about what this dog looks like.  You know it's a dog, you know it's there, you know you can see it, but any further information about it isn't retained in your mind.",
    "default_faction": "dog",
    "bodytype": "dog",
    "categories": [ "WILDLIFE" ],
    "species": [ "MAMMAL" ],
    "volume": "16000 ml",
    "weight": "16 kg",    
    "harvest": "dog_with_skull_fur",
    "dissect": "dissect_lupine_sample_single",
    "hp": 30,
    "speed": 150,
    "material": [ "flesh" ],
    "symbol": "d",
    "color": "light_gray",
    "aggression": -10,
    "morale": 15,
    "aggro_character": false,
    "melee_skill": 6,
    "melee_dice": 2,
    "melee_dice_sides": 3,
    "melee_damage": [ { "damage_type": "cut", "amount": 3 } ],
    "dodge": 3,
    "vision_night": 5,
    "zombify_into": "mon_zombie_dog",
    "death_drops": "mon_dog_death_drops",
    "families": [ "prof_intro_biology" ],
    "path_settings": { "max_dist": 10 },
    "reproduction": { "baby_monster": "mon_dog_pup", "baby_count": 4, "baby_timer": 270 },
    "//": "1-4 puppies & 270 days per-litter for size small canines",
    "baby_flags": [ "SPRING", "SUMMER", "AUTUMN", "WINTER" ],
    "biosignature": { "biosig_item": "feces_dog", "biosig_timer": 6 },
    "anger_triggers": [ "HURT", "FRIEND_ATTACKED", "FRIEND_DIED" ],
    "special_attacks": [ [ "EAT_FOOD", 100 ], [ "PARROT_AT_DANGER", 0 ] ],
    "petfood": {
      "food": [ "DOGFOOD" ],
      "feed": "The %s seems to like you!  It lets you pat its head and seems friendly.",
      "pet": "The %s happily wags its tail while you pat its head."
    },
    "flags": [
      "ANIMAL",
      "DOGFOOD",
      "CANPLAY",
      "CAN_BE_CULLED",
      "GROUP_MORALE",
      "HEARS",
      "PET_MOUNTABLE",
      "HIT_AND_RUN",
      "KEENNOSE",
      "PATH_AVOID_DANGER_1",
      "SEES",
      "SMELLS",
      "SWARMS",
      "WARM",
      "CORNERED_FIGHTER"
    ]
  }
]
